torchvision_extra_decoders/__init__.py
torchvision_extra_decoders/extra_decoders_lib.so
torchvision_extra_decoders/version.py
torchvision_extra_decoders-0.0.2.dist-info/LICENSE
torchvision_extra_decoders-0.0.2.dist-info/METADATA
torchvision_extra_decoders-0.0.2.dist-info/WHEEL
torchvision_extra_decoders-0.0.2.dist-info/top_level.txt
torchvision_extra_decoders-0.0.2.dist-info/RECORD
torchvision_extra_decoders.libs/libavif-bb5c1032.so.16.1.1
torchvision_extra_decoders.libs/libde265-96afb4c7.so
torchvision_extra_decoders.libs/libdav1d-a038bbe0.so.6.9.0
torchvision_extra_decoders.libs/libx265-1b2defb7.so.199
torchvision_extra_decoders.libs/libSvtAv1Enc-ae7609c6.so.2.3.0
torchvision_extra_decoders.libs/libheif-2d9eee16.so.1.18.2
torchvision_extra_decoders.libs/librav1e-0a7d01fc.so.0.6.6
torchvision_extra_decoders.libs/libaom-691b3119.so.3.9.1
