Metadata-Version: 2.1
Name: torchvision-extra-decoders
Version: 0.0.2
Summary: An extension of torchvision for decoding AVIF and HEIC images.
Home-page: https://github.com/pytorch-labs/torchvision-extra-decoders/
Author: PyTorch Team
Author-email: packages@pytorch.org
License: LGPLv2.1
Requires-Python: >=3.9
License-File: LICENSE
